magentism/__init__.py
magentism/agent.py
magentism/agent_call.py
magentism/call_config.py
magentism/computable.py
magentism/computation_decorator.py
magentism/config.py
magentism/constants.py
magentism/exceptions.py
magentism/global_config.py
magentism/llm.py
magentism/magentism.cpython-312-x86_64-linux-gnu.so
magentism-0.4.12.dist-info/METADATA
magentism-0.4.12.dist-info/WHEEL
magentism-0.4.12.dist-info/top_level.txt
magentism-0.4.12.dist-info/RECORD
